mkdocsi/__init__.py
mkdocsi-1.4.5.dist-info/METADATA
mkdocsi-1.4.5.dist-info/WHEEL
mkdocsi-1.4.5.dist-info/entry_points.txt
mkdocsi-1.4.5.dist-info/top_level.txt
mkdocsi-1.4.5.dist-info/RECORD
