Metadata-Version: 2.1
Name: mkdocsi
Version: 1.4.5
Summary: convert docs folder to mkdocs site , dynamic nested docs and folders
Home-page: https://gitlab.com/isampypi/mkdocsi
Author: Mhadhbi Issam
Author-email: mhadhbixissam@gmail.com
Classifier: Programming Language :: Python :: 3
Classifier: License :: OSI Approved :: MIT License
Classifier: Operating System :: OS Independent
Requires-Dist: mkdocs
Requires-Dist: mkdocs-material
